LICENSE
README.rst
setup.cfg
setup.py
django_import_export_celery_edx_copy.egg-info/PKG-INFO
django_import_export_celery_edx_copy.egg-info/SOURCES.txt
django_import_export_celery_edx_copy.egg-info/dependency_links.txt
django_import_export_celery_edx_copy.egg-info/not-zip-safe
django_import_export_celery_edx_copy.egg-info/requires.txt
django_import_export_celery_edx_copy.egg-info/top_level.txt
import_export_celery/__init__.py
import_export_celery/admin.py
import_export_celery/admin_actions.py
import_export_celery/apps.py
import_export_celery/model_config.py
import_export_celery/tasks.py
import_export_celery/migrations/0001_initial.py
import_export_celery/migrations/0002_auto_20190923_1132.py
import_export_celery/migrations/0003_exportjob.py
import_export_celery/migrations/0004_exportjob_email_on_completion.py
import_export_celery/migrations/0005_exportjob_site_of_origin.py
import_export_celery/migrations/0006_auto_20191125_1236.py
import_export_celery/migrations/0007_auto_20210210_1831.py
import_export_celery/migrations/__init__.py
import_export_celery/models/__init__.py
import_export_celery/models/exportjob.py
import_export_celery/models/importjob.py